project_stats.py
project_stats-2.0.0.dist-info/DESCRIPTION.rst
project_stats-2.0.0.dist-info/METADATA
project_stats-2.0.0.dist-info/RECORD
project_stats-2.0.0.dist-info/WHEEL
project_stats-2.0.0.dist-info/entry_points.txt
project_stats-2.0.0.dist-info/metadata.json
project_stats-2.0.0.dist-info/top_level.txt
