Metadata-Version: 2.0
Name: project-stats
Version: 2.0.0
Summary: keep track of all your projects
Home-page: https://github.com/xi/project-stats
Author: Tobias Bengfort
Author-email: tobias.bengfort@posteo.de
License: GPLv2+
Platform: UNKNOWN
Classifier: Development Status :: 4 - Beta
Classifier: Environment :: Console
Classifier: Intended Audience :: Developers
Classifier: Operating System :: OS Independent
Classifier: Programming Language :: Python :: 3
Classifier: License :: OSI Approved :: GNU General Public License v2 or later (GPLv2+)
Classifier: Topic :: Utilities
Requires-Dist: aiohttp
Requires-Dist: python-dateutil
Requires-Dist: pyyaml
Provides-Extra: cheesecake
Requires-Dist: cheesecake; extra == 'cheesecake'
